modelcellsignaling-1.0.0.dist-info/licenses/LICENSE
modelcellsignaling-1.0.0.dist-info/licenses/LICENSE_Llama3
modelcellsignaling-1.0.0.dist-info/licenses/NOTICE
src/data_processing/__init__.py
src/data_processing/data_processing.py
src/generator/__init__.py
src/generator/cli.py
src/generator/generator.py
src/model/__init__.py
src/model/cli.py
src/model/model.py
src/rule_based_generator/__init__.py
src/rule_based_generator/cli.py
src/rule_based_generator/rule_based_generator.py
src/trainer/__init__.py
src/trainer/cli.py
src/trainer/trainer.py
src/transformations/__init__.py
src/transformations/transformations.py
src/utils/__init__.py
src/utils/utils.py
src/visualizer/__init__.py
src/visualizer/visualizer.py
modelcellsignaling-1.0.0.dist-info/METADATA
modelcellsignaling-1.0.0.dist-info/WHEEL
modelcellsignaling-1.0.0.dist-info/entry_points.txt
modelcellsignaling-1.0.0.dist-info/top_level.txt
modelcellsignaling-1.0.0.dist-info/RECORD
