Metadata-Version: 2.4
Name: modelcellsignaling
Version: 1.0.0
Summary: Generator for biological experiments
Home-page: https://github.com/MichalMaszkowski/ZPP
Author: Zuz Kiczak, Michał Korniak, Adam Jaskuła
Author-email: Adam Jaskuła <aj429467@students.mimuw.edu.pl>, Michał Korniak <mk448287@students.mimuw.edu.pl>, Zuz Kiczak <zk439532@students.mimuw.edu.pl>
License-Expression: MIT
Project-URL: Homepage, https://github.com/M-Korniak/ZPP
Project-URL: Bug-Tracker, https://github.com/M-Korniak/ZPP/issues
Classifier: Programming Language :: Python :: 3.10
Classifier: Intended Audience :: Science/Research
Requires-Python: >=3.6
License-File: LICENSE
License-File: LICENSE_Llama3
License-File: NOTICE
Requires-Dist: clearml~=1.10.1
Requires-Dist: gdown~=5.2.0
Requires-Dist: imageio~=2.31.5
Requires-Dist: matplotlib~=3.8.4
Requires-Dist: numpy<2.0
Requires-Dist: pandas==2.2.2
Requires-Dist: pytest~=8.1.0
Requires-Dist: scipy<1.14
Requires-Dist: torch~=2.2.0
Requires-Dist: torchvision~=0.17.0
Requires-Dist: tqdm~=4.67.1
Dynamic: author
Dynamic: home-page
Dynamic: license-file
Dynamic: requires-python
